<repast.simphony.data2.engine.DataSetDescriptor simphonyVersion="2.7.0">
  <name>Keys</name>
  <type>AGGREGATE</type>
  <inclTick>false</inclTick>
  <inclBatchRun>false</inclBatchRun>
  <inclRandomSeed>false</inclRandomSeed>
  <scheduleParams>
    <start>Infinity</start>
    <interval>0.0</interval>
    <priority>-Infinity</priority>
    <pType>LAST</pType>
    <duration>-1.0</duration>
    <frequency>ONE_TIME</frequency>
    <hashCode>14867484</hashCode>
  </scheduleParams>
  <atEnd>false</atEnd>
  <methodDataSources class="linked-hash-map">
    <entry>
      <string>avgKeys</string>
      <repast.simphony.data2.engine.MethodDataSourceDefinition>
        <id>avgKeys</id>
        <className>chord.Node</className>
        <methodName>avgKeys</methodName>
        <aggType>MEAN</aggType>
      </repast.simphony.data2.engine.MethodDataSourceDefinition>
    </entry>
    <entry>
      <string>maxKeys</string>
      <repast.simphony.data2.engine.MethodDataSourceDefinition>
        <id>maxKeys</id>
        <className>chord.Node</className>
        <methodName>maxKeys</methodName>
        <aggType>MAX</aggType>
      </repast.simphony.data2.engine.MethodDataSourceDefinition>
    </entry>
    <entry>
      <string>minKeys</string>
      <repast.simphony.data2.engine.MethodDataSourceDefinition>
        <id>minKeys</id>
        <className>chord.Node</className>
        <methodName>minKeys</methodName>
        <aggType>MIN</aggType>
      </repast.simphony.data2.engine.MethodDataSourceDefinition>
    </entry>
  </methodDataSources>
  <countSources class="linked-hash-map"/>
  <customNADataSources class="linked-hash-map"/>
  <customAggDataSources class="linked-hash-map"/>
</repast.simphony.data2.engine.DataSetDescriptor>